dapt/__init__.py
dapt/config.py
dapt/param.py
dapt/tools.py
dapt/db/__init__.py
dapt/db/base.py
dapt/db/delimited_file.py
dapt/db/sheets.py
dapt/storage/__init__.py
dapt/storage/base.py
dapt/storage/box.py
dapt/storage/google_drive.py
dapt-0.9.2.dist-info/LICENSE
dapt-0.9.2.dist-info/METADATA
dapt-0.9.2.dist-info/WHEEL
dapt-0.9.2.dist-info/top_level.txt
dapt-0.9.2.dist-info/RECORD
