Metadata-Version: 2.1
Name: dapt
Version: 0.9.2
Summary: A library enabling teams to distributed parameter sets between computational resources for faster parameter testing
Home-page: https://github.com/BenSDuggan/DAPT
Author: Ben S. Duggan
Author-email: dugganbens@gmail.com
License: BSD 3-clause "New" or "Revised" license
Keywords: paramater,testing,distributed,crowdsorcing
Platform: UNKNOWN
Classifier: Programming Language :: Python :: 3
Classifier: License :: OSI Approved :: BSD License
Classifier: Operating System :: OS Independent
Requires-Python: >=3.6
Requires-Dist: boxsdk (>=2.0.0)
Requires-Dist: flask (>=1.0.2)
Requires-Dist: gspread (>=3.1.0)
Requires-Dist: oauth2client (>=4.1.3)
Requires-Dist: google-api-python-client (>=1.10.0)
Requires-Dist: google-auth-httplib2 (>=0.0.4)
Requires-Dist: google-auth-oauthlib (>=0.4.1)
